setup.cfg
setup.py
EinsPy.egg-info/PKG-INFO
EinsPy.egg-info/SOURCES.txt
EinsPy.egg-info/dependency_links.txt
EinsPy.egg-info/entry_points.txt
EinsPy.egg-info/not-zip-safe
EinsPy.egg-info/requires.txt
EinsPy.egg-info/top_level.txt
eins/__init__.py
eins/_tips.py
eins/plot.py
eins/road.py
eins/statistics.py
eins/temp.py
eins/testEnter.py
eins/testplot.py