Metadata-Version: 1.1
Name: EinsPy
Version: 1.1.dev0
Summary: Simulations of Traffic System Based on the Theory of Cellular Automaton
Home-page: https://github.com/xiongbeer/Eins
Author: xiongbeer
Author-email: xiongshaoliu@163.com
License: MIT
Platform: UNKNOWN
Classifier: License :: OSI Approved :: MIT License
Classifier: Development Status :: 3 - Alpha
Classifier: Natural Language :: Chinese (Simplified)
Classifier: Programming Language :: Python :: 2.7
Classifier: Topic :: Scientific/Engineering :: Mathematics
